py_predpurchase/__init__.py
py_predpurchase/function_classification_metrics.py
py_predpurchase/function_feature_importance.py
py_predpurchase/function_model_cross_val.py
py_predpurchase/function_preprocessing.py
py_predpurchase-0.2.0.dist-info/LICENSE
py_predpurchase-0.2.0.dist-info/METADATA
py_predpurchase-0.2.0.dist-info/WHEEL
py_predpurchase-0.2.0.dist-info/RECORD
