Metadata-Version: 2.1
Name: py_predpurchase
Version: 0.2.0
Summary: ```py_predpurchase```is a package for predicting online shopper purchasing intentions, containing functions to aid with data analysis processes including conducting data preprocessing as well as calculating classification metrics, cross validation scores and feature importances.The package features functions that focus mainly on analyzing the data and evaluating model performance.
License: MIT
Author: Nour Abdelfattah, Sana Shams, Calvin Choi, Sai Pusuluri
Requires-Python: >=3.9,<4.0
Classifier: License :: OSI Approved :: MIT License
Classifier: Programming Language :: Python :: 3
Classifier: Programming Language :: Python :: 3.9
Classifier: Programming Language :: Python :: 3.10
Classifier: Programming Language :: Python :: 3.11
Classifier: Programming Language :: Python :: 3.12
Requires-Dist: click (>=8.1.7,<9.0.0)
Requires-Dist: numpy (>=1.26.4,<2.0.0)
Requires-Dist: pandas (>=2.2.2,<3.0.0)
Requires-Dist: scikit-learn (>=1.4.2,<2.0.0)
Requires-Dist: tabulate (>=0.9.0,<0.10.0)
